abil/__init__.py
abil/analyze.py
abil/log_grid_search.py
abil/post.py
abil/predict.py
abil/tune.py
abil/unified_tree_or_bag.py
abil/utils.py
abil/zero_stratified_kfold.py
abil/zir.py
abil-25.12.4.dist-info/METADATA
abil-25.12.4.dist-info/WHEEL
abil-25.12.4.dist-info/licenses/LICENSE
abil-25.12.4.dist-info/RECORD
