Metadata-Version: 2.4
Name: abil
Version: 25.12.4
Summary: Aquatic Biogeochemical Interpolation Library
Project-URL: Homepage, https://github.com/nanophyto/Abil
License-Expression: MIT
License-File: LICENSE
Classifier: License :: OSI Approved :: MIT License
Classifier: Operating System :: OS Independent
Classifier: Programming Language :: Python :: 3
Requires-Python: >=3.9
Requires-Dist: dask==2024.5.0
Requires-Dist: netcdf4==1.6.5
Requires-Dist: numpy==1.26.4
Requires-Dist: pandas==2.2.2
Requires-Dist: pyyaml==6.0.1
Requires-Dist: scikit-bio==0.6.2
Requires-Dist: scikit-learn==1.3.0
Requires-Dist: scipy==1.13.1
Requires-Dist: xarray==2023.6.0
Requires-Dist: xgboost==1.7.6
